<system>
	<name>GJ 536</name>
	<rightascension>14 01 03</rightascension>
	<declination>-02 39 18</declination>
	<star>
		<name>GJ 536</name>
		<radius errorminus="-0.05" errorplus="0.05">0.50</radius>
		<magV errorminus="0.009" errorplus="0.009">9.720</magV>
		<magI errorminus="0.008" errorplus="0.008">7.670</magI>
		<magJ errorminus="0.018" errorplus="0.018">6.516</magJ>
		<magH errorminus="0.036" errorplus="0.036">5.935</magH>
		<magK errorminus="0.020" errorplus="0.020">5.683</magK>
		<mass errorminus="-0.05" errorplus="0.05">0.52</mass>
		<temperature errorminus="-68.00" errorplus="68.00">3685.00</temperature>
		<metallicity>-0.080</metallicity>
		<planet>
			<name>GJ 536 b</name>
			<semimajoraxis errorminus="-0.000013" errorplus="0.000011">0.066610</semimajoraxis>
			<eccentricity errorminus="-0.060000" errorplus="0.090000">0.080000</eccentricity>
			<periastron errorminus="-50.6000" errorplus="42.5000">288.7000</periastron>
			<period errorminus="-0.00250000" errorplus="0.00220000">8.70760000</period>
			<mass errorminus="-0.00195" errorplus="0.00217">0.01686</mass>
			<discoverymethod>Radial Velocity</discoverymethod>
			<discoveryyear>2016</discoveryyear>
			<lastupdate>2016-11-17</lastupdate>
		</planet>
	</star>
</system>
